{
    "id": "13",
    "name": "Weedle",
    "type": ["Bug", "Poison"],
    "hp": 40,
    "attack": 35,
    "defense": 30,
    "speed": 50,
    "moves": [
      {
        "name": "Poison Sting",
        "type": "Poison",
        "power": 15,
        "accuracy": 100,
        "effect": "A physical attack that deals damage with a 30% chance to poison the opponent."
      },
      {
        "name": "String Shot",
        "type": "Bug",
        "power": null,
        "accuracy": 95,
        "effect": "Lowers the opponent's speed by one stage."
      }
    ],
    "status": {
      "currentHP": 40,
      "statusCondition": null,
      "statusMultipliers": {
        "attack": 0,
        "defense": 0,
        "speed": 0,
        "evasion": 0,
        "accuracy": 0
      }
    }
  }